english_pkg/Separate_words.py
english_pkg/__init__.py
english_pkg/example.py
english_pkg-1.0.0.dist-info/METADATA
english_pkg-1.0.0.dist-info/WHEEL
english_pkg-1.0.0.dist-info/top_level.txt
english_pkg-1.0.0.dist-info/RECORD
